{
    "attributes": {
        "action": "Fund the creation of more SEN schools",
        "additional_details": "We feel that more needs to be done and that all children should be catered for. No SEN child should be forced to attend and struggle through mainstream school when it is not the right setting for them. We think our SEN children deserve better.",
        "background": "We feel that there are not enough SEN schools to accommodate SEN children. We think there are SEN children struggling through mainstream school and having to be home educated because they simply cannot cope with mainstream school.",
        "closed_at": null,
        "committee_note": "",
        "created_at": "2025-04-19T09:02:41.101Z",
        "creator_name": "Alison Naylor",
        "debate": null,
        "debate_outcome_at": null,
        "debate_threshold_reached_at": null,
        "departments": [
            {
                "acronym": "DfE",
                "name": "Department for Education",
                "url": "https://www.gov.uk/government/organisations/department-for-education"
            }
        ],
        "government_response": null,
        "government_response_at": null,
        "moderation_threshold_reached_at": "2025-04-19T09:28:30.000Z",
        "opened_at": "2025-05-01T10:12:44.098Z",
        "other_parliamentary_business": [],
        "rejected_at": null,
        "rejection": null,
        "response_threshold_reached_at": null,
        "scheduled_debate_date": null,
        "signature_count": 75,
        "signatures_by_constituency": [
            {
                "mp": "Dan Jarvis MP",
                "name": "Barnsley North",
                "ons_code": "E14001074",
                "signature_count": 1
            },
            {
                "mp": "Liam Conlon MP",
                "name": "Beckenham and Penge",
                "ons_code": "E14001083",
                "signature_count": 1
            },
            {
                "mp": "Sir Christopher Chope MP",
                "name": "Christchurch",
                "ons_code": "E14001171",
                "signature_count": 2
            },
            {
                "mp": "Sarah Jones MP",
                "name": "Croydon West",
                "ons_code": "E14001188",
                "signature_count": 1
            },
            {
                "mp": "Ben Obese-Jecty MP",
                "name": "Huntingdon",
                "ons_code": "E14001298",
                "signature_count": 1
            },
            {
                "mp": "Richard Burgon MP",
                "name": "Leeds East",
                "ons_code": "E14001320",
                "signature_count": 2
            },
            {
                "mp": "Rt Hon Rachel Reeves MP",
                "name": "Leeds West and Pudsey",
                "ons_code": "E14001325",
                "signature_count": 1
            },
            {
                "mp": "James MacCleary MP",
                "name": "Lewes",
                "ons_code": "E14001330",
                "signature_count": 1
            },
            {
                "mp": "Greg Smith MP",
                "name": "Mid Buckinghamshire",
                "ons_code": "E14001360",
                "signature_count": 1
            },
            {
                "mp": "George Freeman MP",
                "name": "Mid Norfolk",
                "ons_code": "E14001365",
                "signature_count": 1
            },
            {
                "mp": "Alan Strickland MP",
                "name": "Newton Aycliffe and Spennymoor",
                "ons_code": "E14001382",
                "signature_count": 1
            },
            {
                "mp": "Jon Trickett MP",
                "name": "Normanton and Hemsworth",
                "ons_code": "E14001383",
                "signature_count": 4
            },
            {
                "mp": "Sam Carling MP",
                "name": "North West Cambridgeshire",
                "ons_code": "E14001401",
                "signature_count": 1
            },
            {
                "mp": "Jade Botterill MP",
                "name": "Ossett and Denby Dale",
                "ons_code": "E14001418",
                "signature_count": 1
            },
            {
                "mp": "Rt Hon Yvette Cooper MP",
                "name": "Pontefract, Castleford and Knottingley",
                "ons_code": "E14001428",
                "signature_count": 44
            },
            {
                "mp": "Rt Hon John Healey MP",
                "name": "Rawmarsh and Conisbrough",
                "ons_code": "E14001436",
                "signature_count": 1
            },
            {
                "mp": "Keir Mather MP",
                "name": "Selby",
                "ons_code": "E14001464",
                "signature_count": 6
            },
            {
                "mp": "Emma Lewell MP",
                "name": "South Shields",
                "ons_code": "E14001492",
                "signature_count": 1
            },
            {
                "mp": "Rt Hon David Lammy MP",
                "name": "Tottenham",
                "ons_code": "E14001553",
                "signature_count": 1
            },
            {
                "mp": "Simon Lightwood MP",
                "name": "Wakefield and Rothwell",
                "ons_code": "E14001560",
                "signature_count": 3
            }
        ],
        "signatures_by_country": [
            {
                "code": "GB",
                "name": "United Kingdom",
                "signature_count": 75
            }
        ],
        "signatures_by_region": [
            {
                "name": "North East",
                "ons_code": "A",
                "signature_count": 2
            },
            {
                "name": "Yorkshire and The Humber",
                "ons_code": "D",
                "signature_count": 63
            },
            {
                "name": "East of England",
                "ons_code": "G",
                "signature_count": 3
            },
            {
                "name": "London",
                "ons_code": "H",
                "signature_count": 3
            },
            {
                "name": "South East",
                "ons_code": "J",
                "signature_count": 2
            },
            {
                "name": "South West",
                "ons_code": "K",
                "signature_count": 2
            }
        ],
        "state": "open",
        "topics": [],
        "updated_at": "2025-05-02T14:54:10.000Z"
    },
    "id": 725491,
    "links": {
        "self": "https://petition.parliament.uk/petitions/725491.json"
    },
    "type": "petition"
}