{
    "attributes": {
        "action": "MPs and their families of eligible age be conscripted first before anyone else",
        "additional_details": "To concentrate the minds of those in authority, of the magnitude and the consequences of voting for the imposition of military conscription.",
        "background": "Make it a condition of mandating or parliamentary voting on conscription, that all MPs of eligible age, and their children and families of eligible age, are conscripted first, and sent to the war zone, with evidence to prove this, before anyone else is conscripted.",
        "closed_at": null,
        "committee_note": null,
        "created_at": "2025-10-08T12:43:39.283Z",
        "creator_name": null,
        "debate": null,
        "debate_outcome_at": null,
        "debate_threshold_reached_at": null,
        "departments": [],
        "government_response": null,
        "government_response_at": null,
        "moderation_threshold_reached_at": "2025-10-08T22:30:50.000Z",
        "opened_at": null,
        "rejected_at": "2025-11-12T13:40:31.729Z",
        "rejection": {
            "code": "no-action",
            "details": "The Government has not announced any plans to introduce conscription."
        },
        "response_threshold_reached_at": null,
        "scheduled_debate_date": null,
        "signature_count": 7,
        "state": "rejected",
        "topics": [],
        "updated_at": "2025-11-12T13:40:31.726Z"
    },
    "id": 746111,
    "links": {
        "self": "https://petition.parliament.uk/petitions/746111.json"
    },
    "type": "petition"
}