{
    "attributes": {
        "action": "Stop immigrants rights to work for the first five years of residence in the UK",
        "additional_details": "By taking away the opportunity to come to the UK to take advantage of employment earnings,immigrants should be forced to only come into the country if they have a good reason to be here,apart from the opportunity to make money.\r\nThe working opportunities in the UK promote immigrants to come here just to work,which takes not only jobs but money away from the British citizens.\r\nBy taking away the opportunity to work for five years less immigrants will want to come to the UK,which will give employment back to the british, stopping unemployment figures rising.   ",
        "background": null,
        "closed_at": "2012-09-02T14:18:34.000Z",
        "created_at": "2011-09-02T12:11:54.000Z",
        "debate": null,
        "debate_outcome_at": null,
        "debate_threshold_reached_at": null,
        "government_response": null,
        "government_response_at": null,
        "moderation_threshold_reached_at": "2011-09-02T12:11:54.000Z",
        "opened_at": "2011-09-02T14:18:34.000Z",
        "rejected_at": null,
        "rejection": null,
        "response_threshold_reached_at": null,
        "scheduled_debate_date": null,
        "signature_count": 6,
        "state": "closed",
        "updated_at": "2017-06-21T15:08:10.537Z"
    },
    "id": 15810,
    "links": {
        "self": "https://petition.parliament.uk/archived/petitions/15810.json"
    },
    "type": "archived-petition"
}