{
    "attributes": {
        "action": "Treating Pernicious Anaemia",
        "additional_details": "We call on the Dept. of Health to change the way Pernicious Anaemia is treated away from the current one-size-fits-all format towards a regimen based on the patient's individual needs and where the patient is offered a choice of how he or she receives their replacement therapy B12 including self-administered injections.",
        "background": null,
        "closed_at": "2015-03-30T22:59:59.000Z",
        "created_at": "2014-06-15T05:40:20.000Z",
        "debate": null,
        "debate_outcome_at": null,
        "debate_threshold_reached_at": null,
        "government_response": null,
        "government_response_at": null,
        "moderation_threshold_reached_at": "2014-06-15T05:40:20.000Z",
        "opened_at": "2014-06-16T14:32:57.000Z",
        "rejected_at": null,
        "rejection": null,
        "response_threshold_reached_at": null,
        "scheduled_debate_date": null,
        "signature_count": 1536,
        "state": "closed",
        "updated_at": "2017-06-21T15:15:38.664Z"
    },
    "id": 66406,
    "links": {
        "self": "https://petition.parliament.uk/archived/petitions/66406.json"
    },
    "type": "archived-petition"
}