{
    "attributes": {
        "action": "Keep British Summer Time (BST) all year round",
        "additional_details": "Petition to keep BST all year round.\r\n\r\nThere will be more usable daylight hours in the evening, better driving conditions when more people are commuting at tea-time, less power used so more enviromentally friendly, safer for children to play out for longer in the winter.\r\n\r\nI want the government to scrap the Autumn clock change, and keep British Summer Time.",
        "background": null,
        "closed_at": null,
        "created_at": "2011-08-11T20:47:51.000Z",
        "debate": null,
        "debate_outcome_at": null,
        "debate_threshold_reached_at": null,
        "government_response": null,
        "government_response_at": null,
        "moderation_threshold_reached_at": "2011-08-11T20:47:51.000Z",
        "opened_at": null,
        "rejected_at": "2017-06-21T15:07:09.907Z",
        "rejection": {
            "code": "duplicate",
            "details": null
        },
        "response_threshold_reached_at": null,
        "scheduled_debate_date": null,
        "signature_count": 1,
        "state": "rejected",
        "updated_at": "2017-06-21T15:07:09.910Z"
    },
    "id": 9216,
    "links": {
        "self": "https://petition.parliament.uk/archived/petitions/9216.json"
    },
    "type": "archived-petition"
}