{
    "data": {
        "attributes": {
            "action": "create a fairer council tax system",
            "action_prefix": "We the undersigned petition the Prime Minister to",
            "background": "due to the growing numbers of pensioners and the rising house prices and cost of living burdens already placed on restricted incomes",
            "closed_at": "2007-04-13T00:00:00Z",
            "created_at": "2007-02-13T17:32:07.941397Z",
            "creator_name": "fred",
            "government_response_at": null,
            "government_responses": null,
            "opened_at": "2007-02-13T17:32:07.941397Z",
            "rejected_at": "2007-03-25T00:03:02.718769Z",
            "rejection": {
                "code": 2048,
                "details": "http://petitions.pm.gov.uk/newcounciltax/\nhttp://peitions.pm.gov.uk/counciltaxreform/\nhttp://petitions.pm.gov.uk/ctreform/",
                "reasons": [
                    "Duplicate - this is similar to and/or overlaps with an existing petition or petitions"
                ]
            },
            "signature_count": 1,
            "state": "rejected",
            "updated_at": "2007-10-12T19:10:45.994145Z"
        },
        "id": 2483436
    },
    "links": {
        "original": "http://petitions.number10.gov.uk/harduptaxes/"
    },
    "type": "petition"
}