{
    "attributes": {
        "action": "Make a guarantee for no physical checks at NI side of border nor between GB & NI",
        "additional_details": "http://www.independent.co.uk/news/uk/politics/uk-northern-ireland-border-brexit-eu-hard-no-deal-cabinet-irish-a8235096.html\r\n\r\nhttp://www.independent.co.uk/voices/irish-hard-border-soft-brexit-technology-theresa-may-a8242461.html\r\n\r\nhttp://www.bbc.co.uk/news/uk-politics-43277181\r\n\r\nhttps://www.telegraph.co.uk/politics/2018/02/09/uk-must-set-stone-commitment-no-hard-irish-border-brexit-talks/\r\n\r\nhttps://news.sky.com/story/government-wants-no-changes-to-irish-border-arrangements-10991079",
        "background": "The departure from the EU Customs Union means bilateral customs checks between ROI and UK, UK has promised unilaterally no physical border checks from its side between NI and ROI and NI and GB, this promise should be made into a legal guarantee as part of the so called \"Great Repeal Bill\".",
        "closed_at": null,
        "created_at": "2018-03-07T15:51:31.784Z",
        "creator_name": "Kevin Breslin",
        "debate": null,
        "debate_outcome_at": null,
        "debate_threshold_reached_at": null,
        "government_response": null,
        "government_response_at": null,
        "moderation_threshold_reached_at": "2018-03-07T23:52:01.587Z",
        "opened_at": "2018-03-14T14:20:49.973Z",
        "rejected_at": null,
        "rejection": null,
        "response_threshold_reached_at": null,
        "scheduled_debate_date": null,
        "signature_count": 14,
        "state": "open",
        "updated_at": "2018-03-25T13:22:29.125Z"
    },
    "id": 214521,
    "links": {
        "self": "https://petition.parliament.uk/petitions/214521.json"
    },
    "type": "petition"
}