{
    "attributes": {
        "action": "Make it mandatory to show Iron content on Food Nutrition labels",
        "additional_details": "Due to the iron overload it is important the intake of iron is minimal especially if venesection treatment has not yet happened to avoid the body absorbing more iron which can lead to organ failure and cancer. Whilst the body still needs iron to function it's important to understand what foods are high and low in iron to manage it. At a glance I am unable to find foods high and low in iron currently at the supermarkets. Iron is hardly mentioned when it comes to Food Nutrition.",
        "background": "Haemochromatosis is an inherited condition in which iron levels in the body slowly build up over many years. This build-up of iron, known as iron overload, can cause unpleasant symptoms. If it isn't treated, this can damage parts of the body such as the liver, joints, pancreas and heart.",
        "closed_at": null,
        "created_at": "2019-07-08T18:48:25.428Z",
        "creator_name": "Melita Latham",
        "debate": null,
        "debate_outcome_at": null,
        "debate_threshold_reached_at": null,
        "government_response": null,
        "government_response_at": null,
        "moderation_threshold_reached_at": "2019-07-08T21:16:32.000Z",
        "opened_at": "2019-07-26T15:32:13.365Z",
        "rejected_at": null,
        "rejection": {
            "code": null,
            "details": null
        },
        "response_threshold_reached_at": null,
        "scheduled_debate_date": null,
        "signature_count": 61,
        "signatures_by_constituency": [
            {
                "mp": "John McNally MP",
                "name": "Falkirk",
                "ons_code": "S14000028",
                "signature_count": 1
            },
            {
                "mp": "Lesley Laird MP",
                "name": "Kirkcaldy and Cowdenbeath",
                "ons_code": "S14000041",
                "signature_count": 1
            },
            {
                "mp": "Marion Fellows MP",
                "name": "Motherwell and Wishaw",
                "ons_code": "S14000047",
                "signature_count": 2
            },
            {
                "mp": "Luke Graham MP",
                "name": "Ochil and South Perthshire",
                "ons_code": "S14000050",
                "signature_count": 1
            },
            {
                "mp": "Mhairi Black MP",
                "name": "Paisley and Renfrewshire South",
                "ons_code": "S14000053",
                "signature_count": 1
            },
            {
                "mp": "Pete Wishart MP",
                "name": "Perth and North Perthshire",
                "ons_code": "S14000054",
                "signature_count": 1
            },
            {
                "mp": "Leo Docherty MP",
                "name": "Aldershot",
                "ons_code": "E14000530",
                "signature_count": 1
            },
            {
                "mp": "Rt Hon Damian Green MP",
                "name": "Ashford",
                "ons_code": "E14000536",
                "signature_count": 1
            },
            {
                "mp": "John Woodcock MP",
                "name": "Barrow and Furness",
                "ons_code": "E14000543",
                "signature_count": 1
            },
            {
                "mp": "Helen Goodman MP",
                "name": "Bishop Auckland",
                "ons_code": "E14000569",
                "signature_count": 1
            },
            {
                "mp": "Rt Hon Nick Gibb MP",
                "name": "Bognor Regis and Littlehampton",
                "ons_code": "E14000576",
                "signature_count": 4
            },
            {
                "mp": "Chris Green MP",
                "name": "Bolton West",
                "ons_code": "E14000580",
                "signature_count": 1
            },
            {
                "mp": "Lloyd Russell-Moyle MP",
                "name": "Brighton, Kemptown",
                "ons_code": "E14000597",
                "signature_count": 1
            },
            {
                "mp": "Wayne David MP",
                "name": "Caerphilly",
                "ons_code": "W07000076",
                "signature_count": 1
            },
            {
                "mp": "Gillian Keegan MP",
                "name": "Chichester",
                "ons_code": "E14000633",
                "signature_count": 1
            },
            {
                "mp": "Rt Hon Sir Lindsay Hoyle MP",
                "name": "Chorley",
                "ons_code": "E14000637",
                "signature_count": 1
            },
            {
                "mp": "Rt Hon Mark Harper MP",
                "name": "Forest of Dean",
                "ons_code": "E14000705",
                "signature_count": 1
            },
            {
                "mp": "Rehman Chishti MP",
                "name": "Gillingham and Rainham",
                "ons_code": "E14000711",
                "signature_count": 2
            },
            {
                "mp": "Matthew Pennycook MP",
                "name": "Greenwich and Woolwich",
                "ons_code": "E14000718",
                "signature_count": 1
            },
            {
                "mp": "Rt Hon Robert Halfon MP",
                "name": "Harlow",
                "ons_code": "E14000729",
                "signature_count": 1
            },
            {
                "mp": "Jon Trickett MP",
                "name": "Hemsworth",
                "ons_code": "E14000740",
                "signature_count": 1
            },
            {
                "mp": "Ruth George MP",
                "name": "High Peak",
                "ons_code": "E14000748",
                "signature_count": 1
            },
            {
                "mp": "Graham P Jones MP",
                "name": "Hyndburn",
                "ons_code": "E14000758",
                "signature_count": 2
            },
            {
                "mp": "Rt Hon Jeremy Corbyn MP",
                "name": "Islington North",
                "ons_code": "E14000763",
                "signature_count": 1
            },
            {
                "mp": "Chris Evans MP",
                "name": "Islwyn",
                "ons_code": "W07000077",
                "signature_count": 1
            },
            {
                "mp": "Emma Dent Coad MP",
                "name": "Kensington",
                "ons_code": "E14000768",
                "signature_count": 1
            },
            {
                "mp": "Gerald Jones MP",
                "name": "Merthyr Tydfil and Rhymney",
                "ons_code": "W07000071",
                "signature_count": 2
            },
            {
                "mp": "Mary Glindon MP",
                "name": "North Tyneside",
                "ons_code": "E14000853",
                "signature_count": 1
            },
            {
                "mp": "Chris Elmore MP",
                "name": "Ogmore",
                "ons_code": "W07000074",
                "signature_count": 1
            },
            {
                "mp": "Crispin Blunt MP",
                "name": "Reigate",
                "ons_code": "E14000893",
                "signature_count": 1
            },
            {
                "mp": "Kelly Tolhurst MP",
                "name": "Rochester and Strood",
                "ons_code": "E14000898",
                "signature_count": 4
            },
            {
                "mp": "Rt Hon Philip Hammond MP",
                "name": "Runnymede and Weybridge",
                "ons_code": "E14000907",
                "signature_count": 2
            },
            {
                "mp": "Rebecca Long Bailey MP",
                "name": "Salford and Eccles",
                "ons_code": "E14000911",
                "signature_count": 1
            },
            {
                "mp": "Gordon Henderson MP",
                "name": "Sittingbourne and Sheppey",
                "ons_code": "E14000927",
                "signature_count": 1
            },
            {
                "mp": "Julian Knight MP",
                "name": "Solihull",
                "ons_code": "E14000931",
                "signature_count": 1
            },
            {
                "mp": "Lucy Frazer MP",
                "name": "South East Cambridgeshire",
                "ons_code": "E14000937",
                "signature_count": 1
            },
            {
                "mp": "Mrs Sheryll Murray MP",
                "name": "South East Cornwall",
                "ons_code": "E14000938",
                "signature_count": 1
            },
            {
                "mp": "Rt Hon Robert Buckland MP",
                "name": "South Swindon",
                "ons_code": "E14000947",
                "signature_count": 1
            },
            {
                "mp": "Sir David Amess MP",
                "name": "Southend West",
                "ons_code": "E14000957",
                "signature_count": 4
            },
            {
                "mp": "Alex Cunningham MP",
                "name": "Stockton North",
                "ons_code": "E14000970",
                "signature_count": 1
            },
            {
                "mp": "Kate Green MP",
                "name": "Stretford and Urmston",
                "ons_code": "E14000979",
                "signature_count": 1
            },
            {
                "mp": "Kevin Hollinrake MP",
                "name": "Thirsk and Malton",
                "ons_code": "E14000993",
                "signature_count": 1
            },
            {
                "mp": "Harriett Baldwin MP",
                "name": "West Worcestershire",
                "ons_code": "E14001035",
                "signature_count": 1
            },
            {
                "mp": "Sue Hayman MP",
                "name": "Workington",
                "ons_code": "E14001053",
                "signature_count": 1
            },
            {
                "mp": "Hugh Gaffney MP",
                "name": "Coatbridge, Chryston and Bellshill",
                "ons_code": "S14000011",
                "signature_count": 2
            },
            {
                "mp": "Stuart C. McDonald MP",
                "name": "Cumbernauld, Kilsyth and Kirkintilloch East",
                "ons_code": "S14000012",
                "signature_count": 1
            }
        ],
        "signatures_by_country": [
            {
                "code": "GB",
                "name": "United Kingdom",
                "signature_count": 63
            }
        ],
        "state": "open",
        "updated_at": "2019-07-27T08:33:52.000Z"
    },
    "id": 267013,
    "links": {
        "self": "https://petition.parliament.uk/petitions/267013.json"
    },
    "type": "petition"
}