{
    "data": {
        "attributes": {
            "action": "STOP LANSDOWNE HEDGE FUND'S  SHORTING OF PRUDENTIAL plc",
            "action_prefix": "We the undersigned petition the Prime Minister to",
            "background": "The title say's it all!\nThe public now knows the 'share shorting game' and the damage it does to ORDINARY PEOPLE that pay for the damage caused in extra taxation. \nPrivate Profits at the expense of ALL that matter and vote.",
            "closed_at": "2010-01-04T00:00:00Z",
            "created_at": "2009-10-04T01:44:24.215831Z",
            "creator_name": "Mr A Doyle",
            "government_response_at": null,
            "government_responses": null,
            "opened_at": "2009-10-04T01:44:24.215831Z",
            "rejected_at": "2009-11-07T00:01:01.648591Z",
            "rejection": {
                "code": 32768,
                "details": "We cannot accept your petition as it does not relate to Government policy. You may wish to reword your petition to address Government policy on the general issue of share shorting eg: http://petitions.number10.gov.uk/shortsell/",
                "reasons": [
                    "Intended to be humorous, or has no point about government policy"
                ]
            },
            "signature_count": 1,
            "state": "rejected",
            "updated_at": "2009-11-07T00:01:01.648591Z"
        },
        "id": 13518516
    },
    "links": {
        "original": "http://petitions.number10.gov.uk/PRUDENTIAL/"
    },
    "type": "petition"
}